progressor.py
progressor-0.1.19.dist-info/METADATA
progressor-0.1.19.dist-info/RECORD
progressor-0.1.19.dist-info/WHEEL
progressor-0.1.19.dist-info/top_level.txt
