Metadata-Version: 2.1
Name: progressor
Version: 0.1.19
Summary: A visually appealing progress bar for long lasting computations.
Home-page: https://github.com/JosuaKrause/progressor
Author: Josua Krause
Author-email: josua.krause@gmail.com
License: MIT
Keywords: visual progress bar time estimation
Platform: UNKNOWN
Classifier: Development Status :: 4 - Beta
Classifier: License :: OSI Approved :: MIT License
Classifier: Programming Language :: Python :: 2
Classifier: Programming Language :: Python :: 2.6
Classifier: Programming Language :: Python :: 2.7
Classifier: Programming Language :: Python :: 3
